{
  "date": "2026-07-21",
  "generated": "2026-07-21T23:47:32",
  "games": [
    {
      "game_pk": 824409,
      "game_time": "2026-07-21T22:40:00Z",
      "venue": "Progressive Field",
      "lat": 41.495861,
      "lon": -81.685255,
      "lineup_ids": {
        "away": [
          668885,
          621439,
          680777,
          605137,
          668904,
          605170,
          665019,
          807712,
          668952
        ],
        "home": [
          680757,
          677587,
          800050,
          656555,
          681807,
          683953,
          672356,
          595978,
          690984
        ]
      },
      "away": {
        "team": "Twins",
        "team_full": "Minnesota Twins",
        "abbr": "MIN",
        "team_id": 142,
        "record": "49-52",
        "pitcher_id": 696070,
        "pitcher_name": "Kendry Rojas",
        "pitcher_hand": "L",
        "ml": null,
        "implied": null
      },
      "home": {
        "team": "Guardians",
        "team_full": "Cleveland Guardians",
        "abbr": "CLE",
        "team_id": 114,
        "record": "53-48",
        "pitcher_id": 800048,
        "pitcher_name": "Parker Messick",
        "pitcher_hand": "L",
        "ml": null,
        "implied": null
      },
      "weather": {
        "temp_f": 80.7,
        "wind_mph": 12.0,
        "wind_dir_deg": 253
      },
      "factors": [
        {
          "m": "+",
          "side": "home",
          "label": "Handedness matchup",
          "text": "Parker Messick holds RHB to a 0.604 OPS; Twins project 86% R-handed today."
        }
      ],
      "lean": "home",
      "weight": 1,
      "read": null,
      "total": null,
      "total_read": null,
      "started": true
    },
    {
      "game_pk": 823437,
      "game_time": "2026-07-21T22:40:00Z",
      "venue": "Citizens Bank Park",
      "lat": 39.90539086,
      "lon": -75.16716957,
      "lineup_ids": {
        "away": [
          660271,
          681624,
          518692,
          571970,
          605141,
          663656,
          669242,
          669743,
          672613
        ],
        "home": [
          607208,
          656941,
          547180,
          664761,
          624641,
          592663,
          669016,
          656537,
          681082
        ]
      },
      "away": {
        "team": "Dodgers",
        "team_full": "Los Angeles Dodgers",
        "abbr": "LAD",
        "team_id": 119,
        "record": "63-38",
        "pitcher_id": 680736,
        "pitcher_name": "Justin Wrobleski",
        "pitcher_hand": "L",
        "ml": null,
        "implied": null
      },
      "home": {
        "team": "Phillies",
        "team_full": "Philadelphia Phillies",
        "abbr": "PHI",
        "team_id": 143,
        "record": "56-45",
        "pitcher_id": 554430,
        "pitcher_name": "Zack Wheeler",
        "pitcher_hand": "R",
        "ml": null,
        "implied": null
      },
      "weather": {
        "temp_f": 74.4,
        "wind_mph": 7.9,
        "wind_dir_deg": 195
      },
      "factors": [],
      "lean": "even",
      "weight": 0,
      "read": null,
      "total": null,
      "total_read": null,
      "started": true
    },
    {
      "game_pk": 822787,
      "game_time": "2026-07-21T23:07:00Z",
      "venue": "Rogers Centre",
      "lat": 43.64155,
      "lon": -79.38915,
      "lineup_ids": {
        "away": [
          650490,
          666018,
          691406,
          656775,
          676356,
          802415,
          810938,
          670764,
          663743
        ],
        "home": [
          664770,
          665489,
          676391,
          543807,
          662139,
          672960,
          678218,
          665926,
          664702
        ]
      },
      "away": {
        "team": "Rays",
        "team_full": "Tampa Bay Rays",
        "abbr": "TB",
        "team_id": 139,
        "record": "57-42",
        "pitcher_id": 656876,
        "pitcher_name": "Drew Rasmussen",
        "pitcher_hand": "R",
        "ml": null,
        "implied": null
      },
      "home": {
        "team": "Blue Jays",
        "team_full": "Toronto Blue Jays",
        "abbr": "TOR",
        "team_id": 141,
        "record": "46-54",
        "pitcher_id": 592332,
        "pitcher_name": "Kevin Gausman",
        "pitcher_hand": "R",
        "ml": null,
        "implied": null
      },
      "weather": {
        "temp_f": 67.2,
        "wind_mph": 5.4,
        "wind_dir_deg": 228
      },
      "factors": [
        {
          "m": "+",
          "side": "away",
          "label": "Handedness matchup",
          "text": "Drew Rasmussen holds RHB to a 0.472 OPS; Blue Jays project 62% R-handed today."
        }
      ],
      "lean": "away",
      "weight": 1,
      "read": null,
      "total": null,
      "total_read": null,
      "started": true
    },
    {
      "game_pk": 824895,
      "game_time": "2026-07-21T23:15:00Z",
      "venue": "Truist Park",
      "lat": 33.890672,
      "lon": -84.467641,
      "lineup_ids": {
        "away": [
          665487,
          630105,
          592518,
          664034,
          701538,
          669134,
          657757,
          593428,
          650859
        ],
        "home": [
          686948,
          645277,
          621566,
          663586,
          671739,
          643289,
          573262,
          676551,
          805347
        ]
      },
      "away": {
        "team": "Padres",
        "team_full": "San Diego Padres",
        "abbr": "SD",
        "team_id": 135,
        "record": "49-51",
        "pitcher_id": 621111,
        "pitcher_name": "Walker Buehler",
        "pitcher_hand": "R",
        "ml": null,
        "implied": null
      },
      "home": {
        "team": "Braves",
        "team_full": "Atlanta Braves",
        "abbr": "ATL",
        "team_id": 144,
        "record": "58-41",
        "pitcher_id": 625643,
        "pitcher_name": "Reynaldo L\u00f3pez",
        "pitcher_hand": "R",
        "ml": null,
        "implied": null
      },
      "weather": {
        "temp_f": 88.5,
        "wind_mph": 8.3,
        "wind_dir_deg": 178
      },
      "factors": [
        {
          "m": "+",
          "side": "home",
          "label": "Handedness matchup",
          "text": "Reynaldo L\u00f3pez holds RHB to a 0.659 OPS; Padres project 62% R-handed today."
        }
      ],
      "lean": "home",
      "weight": 1,
      "read": null,
      "total": null,
      "total_read": null,
      "started": true
    },
    {
      "game_pk": 824085,
      "game_time": "2026-07-21T23:40:00Z",
      "venue": "Kauffman Stadium",
      "lat": 39.051567,
      "lon": -94.480483,
      "lineup_ids": {
        "away": [
          671218,
          805811,
          669477,
          646240,
          642715,
          808982,
          683679,
          687551,
          683766
        ],
        "home": [
          695600,
          657041,
          695506,
          521692,
          686469,
          516782,
          686681,
          679845,
          686475
        ]
      },
      "away": {
        "team": "Giants",
        "team_full": "San Francisco Giants",
        "abbr": "SF",
        "team_id": 137,
        "record": "42-58",
        "pitcher_id": 641816,
        "pitcher_name": "Tyler Mahle",
        "pitcher_hand": "R",
        "ml": null,
        "implied": null
      },
      "home": {
        "team": "Royals",
        "team_full": "Kansas City Royals",
        "abbr": "KC",
        "team_id": 118,
        "record": "41-60",
        "pitcher_id": 679883,
        "pitcher_name": "Luinder Avila",
        "pitcher_hand": "R",
        "ml": null,
        "implied": null
      },
      "weather": {
        "temp_f": 88.1,
        "wind_mph": 12.0,
        "wind_dir_deg": 351
      },
      "factors": [],
      "lean": "even",
      "weight": 0,
      "read": null,
      "total": null,
      "total_read": null,
      "started": true
    },
    {
      "game_pk": 823760,
      "game_time": "2026-07-21T23:40:00Z",
      "venue": "American Family Field",
      "lat": 43.02838,
      "lon": -87.97099,
      "lineup_ids": {
        "away": [
          805999,
          665742,
          666182,
          596019,
          701807,
          673357,
          676724,
          543760,
          620443
        ],
        "home": [
          694192,
          668930,
          661388,
          683734,
          669003,
          596142,
          800325,
          806198,
          687401
        ]
      },
      "away": {
        "team": "Mets",
        "team_full": "New York Mets",
        "abbr": "NYM",
        "team_id": 121,
        "record": "42-59",
        "pitcher_id": 804267,
        "pitcher_name": "Zac Thornton",
        "pitcher_hand": "L",
        "ml": null,
        "implied": null
      },
      "home": {
        "team": "Brewers",
        "team_full": "Milwaukee Brewers",
        "abbr": "MIL",
        "team_id": 158,
        "record": "63-37",
        "pitcher_id": 687075,
        "pitcher_name": "Brandon Sproat",
        "pitcher_hand": "R",
        "ml": null,
        "implied": null
      },
      "weather": {
        "temp_f": 77.7,
        "wind_mph": 14.4,
        "wind_dir_deg": 7
      },
      "factors": [
        {
          "m": "+",
          "side": "away",
          "label": "Handedness matchup",
          "text": "Zac Thornton holds RHB to a 0.551 OPS; Brewers project 75% R-handed today."
        }
      ],
      "lean": "away",
      "weight": 1,
      "read": null,
      "total": null,
      "total_read": null,
      "started": true
    },
    {
      "game_pk": 824652,
      "game_time": "2026-07-22T00:05:00Z",
      "venue": "Wrigley Field",
      "lat": 41.948171,
      "lon": -87.655503,
      "lineup_ids": {
        "away": [
          650402,
          805808,
          701678,
          693307,
          682985,
          679529,
          663837,
          701162,
          668670
        ],
        "home": [
          691718,
          673548,
          608324,
          608348,
          683737,
          663538,
          664023,
          621020,
          682634
        ]
      },
      "away": {
        "team": "Tigers",
        "team_full": "Detroit Tigers",
        "abbr": "DET",
        "team_id": 116,
        "record": "47-53",
        "pitcher_id": 664285,
        "pitcher_name": "Framber Valdez",
        "pitcher_hand": "L",
        "ml": 102,
        "implied": 49.5
      },
      "home": {
        "team": "Cubs",
        "team_full": "Chicago Cubs",
        "abbr": "CHC",
        "team_id": 112,
        "record": "56-44",
        "pitcher_id": 656849,
        "pitcher_name": "David Peterson",
        "pitcher_hand": "L",
        "ml": -123,
        "implied": 55.2
      },
      "weather": {
        "temp_f": 74.9,
        "wind_mph": 8.2,
        "wind_dir_deg": 351
      },
      "factors": [
        {
          "m": "-",
          "side": "home",
          "label": "Handedness matchup",
          "text": "David Peterson is vulnerable to RHB (0.821 OPS) and Tigers skew R-handed."
        }
      ],
      "lean": "away",
      "weight": 1,
      "read": null,
      "total": {
        "line": 7.5,
        "over": -112,
        "under": -108
      },
      "total_read": {
        "side": null,
        "strength": 0,
        "line": 7.5,
        "note": "Total 7.5: no clear lean \u2014 not enough data yet. (Bullpen still to come.)"
      },
      "started": false,
      "odds_book": "DraftKings"
    },
    {
      "game_pk": 822871,
      "game_time": "2026-07-22T00:05:00Z",
      "venue": "Globe Life Field",
      "lat": 32.747299,
      "lon": -97.081818,
      "lineup_ids": {
        "away": [
          803011,
          808959,
          678246,
          695731,
          643217,
          671976,
          805367,
          682668,
          691011
        ],
        "home": [
          694671,
          679822,
          673962,
          607043,
          669394,
          677649,
          695508,
          553869,
          696030
        ]
      },
      "away": {
        "team": "White Sox",
        "team_full": "Chicago White Sox",
        "abbr": "CWS",
        "team_id": 145,
        "record": "53-46",
        "pitcher_id": 702273,
        "pitcher_name": "Noah Schultz",
        "pitcher_hand": "L",
        "ml": -105,
        "implied": 51.2
      },
      "home": {
        "team": "Rangers",
        "team_full": "Texas Rangers",
        "abbr": "TEX",
        "team_id": 140,
        "record": "50-50",
        "pitcher_id": 677958,
        "pitcher_name": "Kumar Rocker",
        "pitcher_hand": "R",
        "ml": -114,
        "implied": 53.3
      },
      "weather": null,
      "factors": [
        {
          "m": "-",
          "side": "away",
          "label": "Handedness matchup",
          "text": "Noah Schultz is vulnerable to RHB (0.810 OPS) and Rangers skew R-handed."
        }
      ],
      "lean": "home",
      "weight": 1,
      "read": null,
      "total": {
        "line": 8.5,
        "over": -118,
        "under": -102
      },
      "total_read": {
        "side": "over",
        "strength": 1,
        "line": 8.5,
        "note": "Total 8.5: leans OVER \u2014 both starters look hittable (avg 0.834 OPS-against). (Bullpen still to come.)"
      },
      "started": false,
      "odds_book": "DraftKings"
    },
    {
      "game_pk": 824165,
      "game_time": "2026-07-22T00:10:00Z",
      "venue": "Daikin Park",
      "lat": 29.756967,
      "lon": -95.355509,
      "lineup_ids": {
        "away": [
          672640,
          669065,
          681715,
          669364,
          689414,
          665052,
          805300,
          691594,
          691788
        ],
        "home": [
          665161,
          670541,
          670623,
          514888,
          664774,
          572233,
          666211,
          828599,
          543877
        ]
      },
      "away": {
        "team": "Marlins",
        "team_full": "Miami Marlins",
        "abbr": "MIA",
        "team_id": 146,
        "record": "52-49",
        "pitcher_id": 663969,
        "pitcher_name": "Tyler Phillips",
        "pitcher_hand": "R",
        "ml": 102,
        "implied": 49.5
      },
      "home": {
        "team": "Astros",
        "team_full": "Houston Astros",
        "abbr": "HOU",
        "team_id": 117,
        "record": "48-54",
        "pitcher_id": 837227,
        "pitcher_name": "Tatsuya Imai",
        "pitcher_hand": "R",
        "ml": -123,
        "implied": 55.2
      },
      "weather": null,
      "factors": [
        {
          "m": "-",
          "side": "home",
          "label": "Handedness matchup",
          "text": "Tatsuya Imai is vulnerable to LHB (0.849 OPS) and Marlins skew L-handed."
        }
      ],
      "lean": "away",
      "weight": 1,
      "read": null,
      "total": {
        "line": 9.5,
        "over": 102,
        "under": -122
      },
      "total_read": {
        "side": null,
        "strength": 0,
        "line": 9.5,
        "note": "Total 9.5: no clear lean \u2014 not enough data yet. (Bullpen still to come.)"
      },
      "started": false,
      "odds_book": "DraftKings"
    },
    {
      "game_pk": 824329,
      "game_time": "2026-07-22T00:40:00Z",
      "venue": "Coors Field",
      "lat": 39.756042,
      "lon": -104.994136,
      "lineup_ids": {
        "away": [
          695578,
          671277,
          677588,
          682928,
          678554,
          695734,
          660688,
          683083,
          696285
        ],
        "home": [
          664983,
          694249,
          696100,
          650489,
          681198,
          691720,
          666160,
          687859,
          678662
        ]
      },
      "away": {
        "team": "Nationals",
        "team_full": "Washington Nationals",
        "abbr": "WSH",
        "team_id": 120,
        "record": "51-50",
        "pitcher_id": 687223,
        "pitcher_name": "Carson Palmquist",
        "pitcher_hand": "L",
        "ml": -115,
        "implied": 53.5
      },
      "home": {
        "team": "Rockies",
        "team_full": "Colorado Rockies",
        "abbr": "COL",
        "team_id": 115,
        "record": "40-62",
        "pitcher_id": 547179,
        "pitcher_name": "Michael Lorenzen",
        "pitcher_hand": "R",
        "ml": -105,
        "implied": 51.2
      },
      "weather": null,
      "factors": [
        {
          "m": "-",
          "side": "home",
          "label": "Handedness matchup",
          "text": "Michael Lorenzen is vulnerable to LHB (0.993 OPS) and Nationals skew L-handed."
        }
      ],
      "lean": "away",
      "weight": 1,
      "read": null,
      "total": {
        "line": 13.0,
        "over": -118,
        "under": -102
      },
      "total_read": {
        "side": "over",
        "strength": 2,
        "line": 13.0,
        "note": "Total 13.0: leans OVER \u2014 both starters look hittable (avg 0.857 OPS-against); Coors Field plays hitter-friendly. (Bullpen still to come.)"
      },
      "started": false,
      "odds_book": "DraftKings"
    },
    {
      "game_pk": 824005,
      "game_time": "2026-07-22T01:38:00Z",
      "venue": "Angel Stadium",
      "lat": 33.80019044,
      "lon": -117.8823996,
      "lineup_ids": {
        "away": [
          802139,
          671056,
          676475,
          691023,
          663457,
          691026,
          701675,
          691458,
          663494
        ],
        "home": [
          687263,
          545361,
          694384,
          624585,
          687093,
          666176,
          672724,
          642350,
          681351
        ]
      },
      "away": {
        "team": "Cardinals",
        "team_full": "St. Louis Cardinals",
        "abbr": "STL",
        "team_id": 138,
        "record": "51-48",
        "pitcher_id": 669461,
        "pitcher_name": "Matthew Liberatore",
        "pitcher_hand": "L",
        "ml": 101,
        "implied": 49.8
      },
      "home": {
        "team": "Angels",
        "team_full": "Los Angeles Angels",
        "abbr": "LAA",
        "team_id": 108,
        "record": "40-61",
        "pitcher_id": 700712,
        "pitcher_name": "Walbert Ure\u00f1a",
        "pitcher_hand": "R",
        "ml": -122,
        "implied": 55.0
      },
      "weather": null,
      "factors": [
        {
          "m": "-",
          "side": "away",
          "label": "Handedness matchup",
          "text": "Matthew Liberatore is vulnerable to RHB (0.790 OPS) and Angels skew R-handed."
        }
      ],
      "lean": "home",
      "weight": 1,
      "read": null,
      "total": {
        "line": 9.0,
        "over": -122,
        "under": 101
      },
      "total_read": {
        "side": null,
        "strength": 0,
        "line": 9.0,
        "note": "Total 9.0: no clear lean \u2014 not enough data yet. (Bullpen still to come.)"
      },
      "started": false,
      "odds_book": "DraftKings"
    },
    {
      "game_pk": 825056,
      "game_time": "2026-07-22T01:40:00Z",
      "venue": "Chase Field",
      "lat": 33.445302,
      "lon": -112.066687,
      "lineup_ids": {
        "away": [
          805779,
          691016,
          669127,
          641680,
          695720,
          691777,
          703607,
          671732,
          675961
        ],
        "home": [
          606466,
          672695,
          682998,
          672515,
          596146,
          571448,
          694374,
          545121,
          678489
        ]
      },
      "away": {
        "team": "Athletics",
        "team_full": "Athletics",
        "abbr": "ATH",
        "team_id": 133,
        "record": "43-57",
        "pitcher_id": 678022,
        "pitcher_name": "Jack Perkins",
        "pitcher_hand": "R",
        "ml": 114,
        "implied": 46.7
      },
      "home": {
        "team": "D-backs",
        "team_full": "Arizona Diamondbacks",
        "abbr": "AZ",
        "team_id": 109,
        "record": "51-49",
        "pitcher_id": 684442,
        "pitcher_name": "Kohl Drake",
        "pitcher_hand": "L",
        "ml": -137,
        "implied": 57.8
      },
      "weather": null,
      "factors": [
        {
          "m": "-",
          "side": "away",
          "label": "Handedness matchup",
          "text": "Jack Perkins is vulnerable to RHB (0.833 OPS) and D-backs skew R-handed."
        }
      ],
      "lean": "home",
      "weight": 1,
      "read": null,
      "total": {
        "line": 9.5,
        "over": -102,
        "under": -118
      },
      "total_read": {
        "side": null,
        "strength": 0,
        "line": 9.5,
        "note": "Total 9.5: no clear lean \u2014 not enough data yet. (Bullpen still to come.)"
      },
      "started": false,
      "odds_book": "DraftKings"
    },
    {
      "game_pk": 823114,
      "game_time": "2026-07-22T01:40:00Z",
      "venue": "T-Mobile Park",
      "lat": 47.591333,
      "lon": -122.33251,
      "lineup_ids": {
        "away": [
          682829,
          701398,
          668709,
          553993,
          663993,
          682622,
          624431,
          670770,
          695490
        ],
        "home": [
          702284,
          668227,
          686527,
          663728,
          647304,
          670042,
          645302,
          806068,
          642215
        ]
      },
      "away": {
        "team": "Reds",
        "team_full": "Cincinnati Reds",
        "abbr": "CIN",
        "team_id": 113,
        "record": "45-54",
        "pitcher_id": 695505,
        "pitcher_name": "Chase Burns",
        "pitcher_hand": "R",
        "ml": -102,
        "implied": 50.5
      },
      "home": {
        "team": "Mariners",
        "team_full": "Seattle Mariners",
        "abbr": "SEA",
        "team_id": 136,
        "record": "51-50",
        "pitcher_id": 622491,
        "pitcher_name": "Luis Castillo",
        "pitcher_hand": "R",
        "ml": -118,
        "implied": 54.1
      },
      "weather": null,
      "factors": [],
      "lean": "even",
      "weight": 0,
      "read": null,
      "total": {
        "line": 7.5,
        "over": -112,
        "under": -108
      },
      "total_read": {
        "side": "under",
        "strength": 2,
        "line": 7.5,
        "note": "Total 7.5: leans UNDER \u2014 both starters suppress contact (avg 0.683 OPS-against); T-Mobile Park plays pitcher-friendly. (Bullpen still to come.)"
      },
      "started": false,
      "odds_book": "DraftKings"
    },
    {
      "game_pk": 823519,
      "game_time": "2026-07-21T23:05:00Z",
      "venue": "Yankee Stadium",
      "lat": 40.82919482,
      "lon": -73.9264977,
      "lineup_ids": {
        "away": [],
        "home": []
      },
      "away": {
        "team": "Pirates",
        "team_full": "Pittsburgh Pirates",
        "abbr": "PIT",
        "team_id": 134,
        "record": "52-49",
        "pitcher_id": 696149,
        "pitcher_name": "Bubba Chandler",
        "pitcher_hand": "R",
        "ml": null,
        "implied": null
      },
      "home": {
        "team": "Yankees",
        "team_full": "New York Yankees",
        "abbr": "NYY",
        "team_id": 147,
        "record": "56-44",
        "pitcher_id": 701542,
        "pitcher_name": "Will Warren",
        "pitcher_hand": "R",
        "ml": null,
        "implied": null
      },
      "weather": {
        "temp_f": 74.9,
        "wind_mph": 8.6,
        "wind_dir_deg": 129
      },
      "factors": [
        {
          "m": "~",
          "side": "none",
          "label": "Lineups",
          "text": "Yankees lineup not posted yet \u2014 handedness matchup firms up ~2-4 hrs before first pitch."
        },
        {
          "m": "~",
          "side": "none",
          "label": "Lineups",
          "text": "Pirates lineup not posted yet \u2014 handedness matchup firms up ~2-4 hrs before first pitch."
        }
      ],
      "lean": "even",
      "weight": 0,
      "read": null,
      "total": null,
      "total_read": null,
      "started": true
    },
    {
      "game_pk": 824735,
      "game_time": "2026-07-21T23:10:00Z",
      "venue": "Fenway Park",
      "lat": 42.346456,
      "lon": -71.097441,
      "lineup_ids": {
        "away": [],
        "home": []
      },
      "away": {
        "team": "Orioles",
        "team_full": "Baltimore Orioles",
        "abbr": "BAL",
        "team_id": 110,
        "record": "49-52",
        "pitcher_id": 680694,
        "pitcher_name": "Kyle Bradish",
        "pitcher_hand": "R",
        "ml": null,
        "implied": null
      },
      "home": {
        "team": "Red Sox",
        "team_full": "Boston Red Sox",
        "abbr": "BOS",
        "team_id": 111,
        "record": "51-48",
        "pitcher_id": 700842,
        "pitcher_name": "Eduardo Rivera",
        "pitcher_hand": "L",
        "ml": null,
        "implied": null
      },
      "weather": {
        "temp_f": 68.9,
        "wind_mph": 6.2,
        "wind_dir_deg": 131
      },
      "factors": [
        {
          "m": "~",
          "side": "none",
          "label": "Lineups",
          "text": "Red Sox lineup not posted yet \u2014 handedness matchup firms up ~2-4 hrs before first pitch."
        },
        {
          "m": "~",
          "side": "none",
          "label": "Lineups",
          "text": "Orioles lineup not posted yet \u2014 handedness matchup firms up ~2-4 hrs before first pitch."
        }
      ],
      "lean": "even",
      "weight": 0,
      "read": null,
      "total": null,
      "total_read": null,
      "started": true
    }
  ]
}